custom_components/reflex_confetti_component/__init__.py
custom_components/reflex_confetti_component/confetti_component.py
custom_components/reflex_confetti_component/confetti_component.pyi
reflex_confetti_component-0.0.1.dist-info/METADATA
reflex_confetti_component-0.0.1.dist-info/WHEEL
reflex_confetti_component-0.0.1.dist-info/top_level.txt
reflex_confetti_component-0.0.1.dist-info/RECORD
