Metadata-Version: 2.4
Name: reflex-confetti-component
Version: 0.0.1
Summary: Reflex custom component confetti-component
Author-email: Your Name <YOUREMAIL@domain.com>
License: Apache-2.0
Keywords: reflex,reflex-custom-components
Classifier: Development Status :: 4 - Beta
Requires-Python: >=3.10
Requires-Dist: reflex>=0.8.7
Provides-Extra: dev
Requires-Dist: build; extra == "dev"
Requires-Dist: twine; extra == "dev"
